{
  "id": "hBJVFBHF",
  "slug": "afk-sleep",
  "title": "AFK Sleep",
  "description": "Sleep while players are idle on your server · Works with custom player sleeping percentages · Handles dimensions, leaving, joining, ...",
  "body": "# AFK Sleep\n\n**Requires [Detect AFK Players](https://modrinth.com/datapack/detect-afk)**.\n\nAllows players to sleep even when there are players AFK on the server, and respects your original `playersSleepingPercentage`. If you've got someone that joins then immediately leaves to take a shower, now that won't stop you from being able to skip the night.\n\n**Features**\n\n- **Configurable percentage** - Change the gamerule like you would normally\n- **Highly optimized** - No commands run unless necessary, no NBT usage, no checks every tick\n- **Reacts to changes** - Leaving, joining, changing AFK state, changing dimension, etc\n- **Works correctly** - Other data packs don't consider dimensions or state changes\n\n![https://cdn.modrinth.com/data/hBJVFBHF/images/a555a85ba89158b0d992c7151b6d811a21493f16.jpeg](https://cdn.modrinth.com/data/hBJVFBHF/images/a555a85ba89158b0d992c7151b6d811a21493f16.jpeg)\n\n## Details\n\nWhen AFK Sleep is first installed, it uses the `playersSleepingPercentage` you've set as the *percentage of non-AFK players in the overworld* that have to be sleeping to skip the night. The table below explains it:\n\n| Players | Not AFK | playersSleepingPercentage | Players required to sleep |\n| -------------- | --------------- | --------------------------------- | -------------------------------- |\n| 3              | 3               | 100%                              | **3** (all three players have to sleep)                                |\n| 3              | 2               | 100%                              | **2** (only the two non-afk players have to sleep)                               |\n| 3              | 2               | 50%                               | **1** (only half of the non-afk players have to sleep)                               |\n\nTo change the percentage of \"active\" players that need to sleep, just change the gamerule like you normally would, with `/gamerule playersSleepingPercentage NUMBER`. This gamerule is managed for you, so don't worry if it isn't set to the value you expect.\n\n<details>\n<summary><strong>Before version 1.3:</strong> How to change playersSleepingPercentage</summary>\n\nBecause this datapack overrides the `playersSleepingPercentage` gamerule, you have to modify a scoreboard value to change its calculations. Replace the number '50' with the percentage you want to set.\n\n```mcfunction\n/scoreboard players set .relativePercentage afk_sleep.dummy 50\n```\n\n</details>\n\nIf you want to uninstall the datapack, run `/function afk_sleep:uninstall` to delete the backing scoreboards and reset the `playersSleepingPercentage` automatically.",
  "categories": [
    "datapack",
    "fabric",
    "forge",
    "game-mechanics",
    "neoforge",
    "quilt",
    "social",
    "utility"
  ],
  "client_side": "unsupported",
  "server_side": "required",
  "downloads": 8136,
  "followers": 0,
  "game_versions": [
    "1.17",
    "1.17.1",
    "1.18",
    "1.18.1",
    "1.18.2",
    "1.19",
    "1.19.1",
    "1.19.2",
    "1.19.3",
    "1.19.4",
    "1.20",
    "1.20.1",
    "1.20.2",
    "1.20.3",
    "1.20.4",
    "1.20.5",
    "1.20.6",
    "1.21",
    "1.21.1",
    "1.21.2",
    "1.21.3",
    "1.21.4",
    "1.21.5",
    "1.21.6",
    "1.21.7",
    "1.21.8"
  ],
  "date_updated": null
}