{
  "id": "xnUMB4rw",
  "slug": "blockvantage",
  "title": "BlockVantage",
  "description": "Successfully Blocking an Attack with a shield Gives you a Huge buff for Small Duration.",
  "body": "Blocking Attack Successfully Will Give you:\n\n<details>\n<summary>Spoiler</summary>\n\n- Speed I I for 2 Seconds\n- Strength V for 3 Seconds\n- Resistance V for 3 Seconds\n\n_**(Effects Dont Stack)**_\n\n</details>\n\n",
  "categories": [
    "adventure",
    "equipment",
    "fabric",
    "game-mechanics",
    "technology",
    "utility"
  ],
  "client_side": "required",
  "server_side": "required",
  "downloads": 906,
  "followers": 0,
  "game_versions": [
    "1.21",
    "1.21.1",
    "1.21.2"
  ],
  "date_updated": null
}