{
  "id": "xHhQihpG",
  "slug": "boathider",
  "title": "BoatHider",
  "description": "Plugin to hide other entities in boats when a player is in a boat. This allows multiple people to go on a single boat course simultaniously without colliding, with no client-side mods neccesary.",
  "body": "# BoatHider\nBoat hiding and boat collision prevention plugin. \n\nCurrently functional on: <br>\n<ul>\n    <li>1.19.4</li>\n    <li>1.20</li>\n    <li>1.20.1</li>\n    <li>1.20.2</li>\n    <li>1.20.3</li>\n    <li>1.20.4</li>\n    <li>1.20.5</li>\n    <li>1.20.6</li>\n    <li>1.21</li>\n</ul>\n\nPRs for bug fixes, version updates, and possible features are welcome.\n\nOpen a github issue if you need this plugin for a particular mc version, too lazy to update unless its needed.",
  "categories": [
    "paper",
    "purpur",
    "spigot"
  ],
  "client_side": "unsupported",
  "server_side": "required",
  "downloads": 321,
  "followers": 0,
  "game_versions": [
    "1.19.4",
    "1.20",
    "1.20.1",
    "1.20.2",
    "1.20.3",
    "1.20.4",
    "1.20.5",
    "1.20.6",
    "1.21"
  ],
  "date_updated": null
}