{
  "id": "i6ylPOr9",
  "slug": "bohrium",
  "title": "Bohrium",
  "description": "Best Modpack For Stable Performance under \"10\" MODS",
  "body": "# A Modpack Made for Stable Minecraft Gameplay\n\nIf you're tired of your Minecraft feeling laggy, stuttery, or inconsistent, this modpack is made exactly for you. Smooth & Stable focuses on delivering a clean, comfortable, and reliable gameplay experience without changing the core feel of the game.\nNo chaos, no unnecessary features just Minecraft, but vanilla smooth.\n\n# System Requirements\n\nLow System Requirements\nWorks great even on older PCs or laptops and also perfect if your hardware isn’t high-end.\n\n\n\n<details>\n<summary>Mods Inc.</summary>\n\n\n- [Cloth Config.](https://modrinth.com/mod/cloth-config)\n- [Complete Config.](https://modrinth.com/mod/completeconfig)\n- [Fabric Api](https://modrinth.com/mod/fabric-api)\n- [Malilib](https://modrinth.com/mod/malilib)\n- [Mod Menu](https://modrinth.com/mod/modmenu)\n- [Reese's Sodium Options](https://modrinth.com/mod/reeses-sodium-options)\n- [Sodium](https://modrinth.com/mod/sodium)\n- [Sodium Extra](https://modrinth.com/mod/sodium-extra)\n\n\n",
  "categories": [
    "fabric",
    "lightweight",
    "multiplayer",
    "optimization"
  ],
  "client_side": "required",
  "server_side": "unsupported",
  "downloads": 167,
  "followers": 0,
  "game_versions": [
    "1.20.2",
    "1.20.4",
    "1.20.5",
    "1.20.6",
    "1.21",
    "1.21.1",
    "1.21.2",
    "1.21.3",
    "1.21.4",
    "1.21.5",
    "1.21.6",
    "1.21.7",
    "1.21.8",
    "1.21.9",
    "1.21.10"
  ],
  "date_updated": null
}