{
  "id": "DATDIjwD",
  "slug": "downfall-enchantment",
  "title": "Downfall Enchantment",
  "description": "New enchantment for boots to make a shockwave when hitting the ground!",
  "body": "# Downfall Enchantment\n\n[![Discord](https://img.shields.io/discord/1327308441324097681?label=discord&color=blue&logo=discord)](https://discord.gg/5UdcDa5xNC)\n[![Modrinth](https://img.shields.io/modrinth/dt/downfall-enchantment?label=modrinth&logo=modrinth)](https://modrinth.com/datapack/downfall-enchantment)\n[![License](https://img.shields.io/github/license/lullaby6/data-packs)](https://github.com/lullaby6/data-packs/blob/main/LICENSE)\n\n## 📖 Description\n\nNew enchantment for boots to make a shockwave when hitting the ground!\n\nThe enchantment can be obtained from the enchantment table, loot chests or trading with villagers.\n\n## 🪪 License\n\n[AGPL-3.0-or-later](https://github.com/lullaby6/data-packs/blob/main/LICENSE)\n\n## 👾 Bugs/Issues\n\nPlease report any problem/bug/issues in the [Discord Server](https://discord.gg/5UdcDa5xNC).\n\n## 💌 Donate\n\n- [Donate on Ko-Fi](https://ko-fi.com/lullaby45743)\n- [Donate on PayPal](https://www.paypal.com/paypalme/lucianobrumer)\n\n## 🎁 Server Hosting\n\nCreating your own server can be a very lengthy, tedious and costly process.\n\nBut with BisectHosting, you get your own server in just a couple of clicks! With their 24/7 support and fast-response time, no issues shall stand in your way!\nInterested? Then we've got a deal for you!\n\nhttps://bisecthosting.com/lullaby\n\n![Server Hosting](https://www.bisecthosting.com/partners/custom-banners/e840cd99-59f6-4b27-b542-3023cd08bdfe.webp)",
  "categories": [
    "adventure",
    "datapack",
    "equipment",
    "fabric",
    "forge",
    "magic",
    "neoforge",
    "quilt"
  ],
  "client_side": "unknown",
  "server_side": "unknown",
  "downloads": 2714,
  "followers": 0,
  "game_versions": [
    "1.21",
    "1.21.1",
    "1.21.2",
    "1.21.3",
    "1.21.4",
    "1.21.5",
    "1.21.6",
    "1.21.7",
    "1.21.8",
    "1.21.9",
    "1.21.10",
    "1.21.11",
    "26.1",
    "26.1.1",
    "26.1.2"
  ],
  "date_updated": null
}