{
  "id": "y7a0E4te",
  "slug": "eldritch-horizons",
  "title": "Eldritch Horizons",
  "description": "Eldritch Horizons is an RPG-focused Fabric 1.20.1 modpack with new biomes, bosses, weapons, and a completely reworked combat system. Created with the help of AI specially for this video.",
  "body": "Eldritch Horizons — Fabric 1.20.1 RPG Modpack\n\nExplore a reimagined Minecraft world with RPG elements:\n\nOverhauled world generation with new biomes and mysterious structures.\n\nA reworked combat system with dodges, parries, and epic weapon animations.\n\nPowerful new mobs, mini-bosses, and eldritch creatures lurking in the dark.\n\nTons of new weapons, armor, and gear to master on your adventure.\n\nThis modpack was designed with the help of AI specifically for this video — combining exploration, combat, and progression into a true RPG experience in Minecraft Fabric 1.20.1.",
  "categories": [
    "adventure",
    "combat",
    "fabric",
    "quests",
    "technology"
  ],
  "client_side": "required",
  "server_side": "required",
  "downloads": 119,
  "followers": 0,
  "game_versions": [
    "1.20.1"
  ],
  "date_updated": null
}