{
  "id": "SVaqKxMw",
  "slug": "elytra-pvp-rebalance",
  "title": "Elytra PVP Rebalance",
  "description": "Elytra time limit in combat, requested by @euxarbi",
  "body": "Intended to prevent players from fleeing PVP with elytra.\n\nWhen a player takes damage (except fall, kinetic, starve, and worldborder) or attacks another player, they will receive an elytra flight time limit of 5 seconds. This lasts for 3 minutes after attacking or taking damage. After 2 minutes of not taking damage or attacking your timer will increase by 1 second every 45 seconds. Performing a mace smash or dismounting spear hit resets the timer to 5 seconds.\n\nAll values are configurable through gamerules.\n\nRequested by @euxarbi on the fabric discord server",
  "categories": [
    "equipment",
    "fabric",
    "game-mechanics",
    "social",
    "transportation"
  ],
  "client_side": "unsupported",
  "server_side": "required",
  "downloads": 572,
  "followers": 0,
  "game_versions": [
    "1.21.11"
  ],
  "date_updated": null
}