{
  "id": "M3h8LJZc",
  "slug": "fresh-entity-textures",
  "title": "fresh entity textures",
  "description": "this texture pack adds new entity textures to your game!",
  "body": "![FET](https://cdn.modrinth.com/data/cached_images/0600ebb677775b8277c3f1c306dcaca04563c459.png)\n# F.E.T.\nWhy should the world of Minecraft feel so static? Fresh Entity Textures is a comprehensive resource pack designed to shatter the \"clone\" feel of the game's mobs. By staying strictly within the pixel-art aesthetic, this pack provides a massive visual upgrade.\n\n## Available on\n[![CurseForge](https://cdn.modrinth.com/data/cached_images/184de7d56945a6412accd3de69ecc948e3795cab.png)](https://www.curseforge.com/minecraft/texture-packs/fresh-entity-textures)\n![to](https://cdn.modrinth.com/data/cached_images/69ab5455887de4967cfbcbad238be13409ba3a0e.png)\n[![modrinth](https://cdn.modrinth.com/data/cached_images/ab59b323749cdde88a44a7018d8c893f13bcc239.png)](https://modrinth.com/resourcepack/fresh-entity-textures)\n\n## 🎨 Enhanced Textures\nFresh Entity Textures doesn't try to turn the game into a high-res horror movie. Instead, it polishes the \"soul\" of the game:\n\nColor Theory Focused: Vibrant, intentional palettes that make mobs pop against the terrain.\n\n## ℹ️ About Creator\nhi my name is _UU_. i love making mods and other things inside minecraft. like this one that i made. i spend so much time so i will be happy if you will support me. ```i recomend use fresh animations with F.E.T.```. thanks for listening.\n\n## 📋 Instruction\n![EMF](https://cdn.modrinth.com/data/cached_images/27f6bbf8bba7b777552bd2cc6688d76f36b69159_0.webp)\n![ETF](https://cdn.modrinth.com/data/cached_images/4a9fe8d33f8dcc4a61abf23919d9c04871f41937.png)\n\n1. install [EMF](https://modrinth.com/mod/entity-model-features)\n2. install [ETF](https://modrinth.com/mod/entitytexturefeatures)\n\n## ⚠️ EMF & ETF Requirements\n[EMF](https://modrinth.com/mod/entity-model-features) and [ETF](https://modrinth.com/mod/entitytexturefeatures) are rquired for that resourcepack if you not gonna install it some things can work incorrectly!\n\n## 📜 Permissions\nyou can use this resourcepack in your modpacks but you can upload it to other mod libraries but if you pretend you are creator. i can report you for copyright.",
  "categories": [
    "16x",
    "entities",
    "minecraft",
    "simplistic",
    "vanilla-like"
  ],
  "client_side": "required",
  "server_side": "unsupported",
  "downloads": 446,
  "followers": 0,
  "game_versions": [
    "1.7.2",
    "1.7.3",
    "1.7.4",
    "1.7.5",
    "1.7.6",
    "1.7.7",
    "1.7.8",
    "1.7.9",
    "1.7.10",
    "1.8",
    "1.8.1",
    "1.8.2",
    "1.8.3",
    "1.8.4",
    "1.8.5",
    "1.8.6",
    "1.8.7",
    "1.8.8",
    "1.8.9",
    "1.9",
    "1.9.1",
    "1.9.2",
    "1.9.3",
    "1.9.4",
    "1.10",
    "1.10.1",
    "1.10.2",
    "1.11",
    "1.11.1",
    "1.11.2",
    "1.12",
    "1.12.1",
    "1.12.2",
    "1.13",
    "1.13.1",
    "1.13.2",
    "1.14",
    "1.14.1",
    "1.14.2",
    "1.14.3",
    "1.14.4",
    "1.15",
    "1.15.1",
    "1.15.2",
    "1.16",
    "1.16.1",
    "1.16.2",
    "1.16.3",
    "1.16.4",
    "1.16.5",
    "1.17",
    "1.17.1",
    "1.18",
    "1.18.1",
    "1.18.2",
    "1.19",
    "1.19.1",
    "1.19.2",
    "22w42a",
    "22w43a",
    "22w44a",
    "1.19.3",
    "1.19.4",
    "23w14a",
    "23w16a",
    "1.20",
    "1.20.1",
    "23w31a",
    "23w32a",
    "23w33a",
    "23w35a",
    "1.20.2-pre1",
    "1.20.2",
    "23w42a",
    "23w43a",
    "23w43b",
    "23w44a",
    "23w45a",
    "23w46a",
    "1.20.3",
    "1.20.4",
    "24w03a",
    "24w03b",
    "24w04a",
    "24w05a",
    "24w05b",
    "24w06a",
    "24w07a",
    "24w09a",
    "24w10a",
    "24w11a",
    "24w12a",
    "24w13a",
    "24w14potato",
    "24w14a",
    "1.20.5-pre1",
    "1.20.5-pre2",
    "1.20.5-pre3",
    "1.20.5",
    "1.20.6",
    "24w18a",
    "24w19a",
    "24w19b",
    "24w20a",
    "1.21-pre1",
    "1.21-pre2",
    "1.21-pre3",
    "1.21-pre4",
    "1.21-rc1",
    "1.21",
    "1.21.1-rc1",
    "1.21.1",
    "24w33a",
    "24w34a",
    "24w35a",
    "24w36a",
    "24w37a",
    "24w38a",
    "24w39a",
    "24w40a",
    "1.21.2-pre1",
    "1.21.2-pre2",
    "1.21.2-pre3",
    "1.21.2-pre4",
    "1.21.2-pre5",
    "1.21.2-rc1",
    "1.21.2-rc2",
    "1.21.2",
    "1.21.3",
    "24w44a",
    "24w45a",
    "24w46a",
    "1.21.4-pre1",
    "1.21.4-pre2",
    "1.21.4-pre3",
    "1.21.4-rc1",
    "1.21.4-rc2",
    "1.21.4-rc3",
    "1.21.4",
    "1.21.5-pre1",
    "1.21.5-pre2",
    "1.21.5-pre3",
    "1.21.5-rc1",
    "1.21.5-rc2",
    "1.21.5",
    "1.21.6-pre1",
    "1.21.6-pre2",
    "1.21.6-pre3",
    "1.21.6-pre4",
    "1.21.6-rc1",
    "1.21.6",
    "1.21.7-rc1",
    "1.21.7-rc2",
    "1.21.7",
    "1.21.8-rc1",
    "1.21.8",
    "1.21.9-pre1",
    "1.21.9-pre2",
    "1.21.9-pre3",
    "1.21.9-pre4",
    "1.21.9-rc1",
    "1.21.9",
    "1.21.10-rc1",
    "1.21.10",
    "25w41a",
    "25w42a",
    "25w43a",
    "25w44a",
    "25w45a",
    "25w46a",
    "1.21.11-pre1",
    "1.21.11-pre2",
    "1.21.11-pre3",
    "1.21.11-pre4",
    "1.21.11-pre5",
    "1.21.11-rc1",
    "1.21.11-rc2",
    "1.21.11-rc3",
    "1.21.11",
    "26.1-snapshot-1",
    "26.1-snapshot-2",
    "26.1-snapshot-3",
    "26.1-snapshot-4",
    "26.1-snapshot-5",
    "26.1-snapshot-6",
    "26.1-snapshot-7",
    "26.1-snapshot-8",
    "26.1-snapshot-9",
    "26.1"
  ],
  "date_updated": null
}