{
  "id": "fR4bi2hg",
  "slug": "locator-name-tags",
  "title": "Locator Name Tags",
  "description": "This mod adds the nicknames of the players who own the markers above the markers on the locator.",
  "body": "**Recently, I released a mod that simplifies movement in the game.**\n**Details:** https://modrinth.com/mod/better-movement-(fabric)\n\n\nThis mod adds nickname rendering above the markers from the recently added locator. It's useful if you want to go to a **specific player**.\n![Preview](https://cdn.modrinth.com/data/cached_images/07cec1ad66db45ee8b2d51f3791b31c15ae6484b.png)",
  "categories": [
    "fabric",
    "game-mechanics",
    "management",
    "utility"
  ],
  "client_side": "required",
  "server_side": "unsupported",
  "downloads": 296,
  "followers": 0,
  "game_versions": [
    "1.21.6",
    "1.21.7"
  ],
  "date_updated": null
}