{
  "id": "g8b7Sxhz",
  "slug": "medieval-smp-s4",
  "title": "medieval smp S4",
  "description": "this is, lets say a sort of \"kitchen sink\" medieval pack, tho not finished",
  "body": "A small side project I made for my friends and myself which includes:\n* all of Epic knights addon\n* farmer's delight \n* the let's do mods (brewery, farm & charm and vinery)\n* immersive mods (subtle effects, dynamic lights, immersive melodies)\n* performance mods\n* and emotes!",
  "categories": [
    "adventure",
    "fabric",
    "kitchen-sink",
    "multiplayer",
    "neoforge"
  ],
  "client_side": "required",
  "server_side": "required",
  "downloads": 107,
  "followers": 0,
  "game_versions": [
    "1.21.1"
  ],
  "date_updated": null
}