{
  "id": "xGCfuSC3",
  "slug": "mind-motion",
  "title": "Ascend: Mind & Motion",
  "description": "A lightweight gameplay systems mod adding Sanity, Insanity, and Tempo.",
  "body": "# Mind & Motion\n\n*A lightweight gameplay systems mod adding Sanity, Insanity, and Tempo.*\n\n## Epilepsy Warning\n\n**Mind & Motion includes occasional screen flashes, distortion, and shader-based visual effects that may be triggered when Sanity becomes low or Insanity becomes high. Players with photosensitive epilepsy or sensitivity to flashing lights should disable visual effects in the mod’s configuration or avoid using the mod.**\n\n## Overview\n\nMind & Motion is a small gameplay-enhancement mod inspired by *Deepwoken*. It introduces three new player attributes: **Sanity**, **Insanity**, and **Tempo**, that respond dynamically to your environment, combat state, and actions. These systems aim to add atmosphere and decision-making without changing core Minecraft progression.\n\nAll features are fully configurable and can be adjusted or disabled depending on your preferred playstyle.\n\n## Features\n\n### Sanity\n* Default maximum: **80**\n* Sanity decreases in specific conditions, such as:\n  * Being in dark or enclosed locations\n  * Encountering certain mobs\n  * Remaining at low health\n* As Sanity falls, **Insanity** rises.\n  * High Insanity cause:\n  * Visual distortion\n  * Ambient audio effects\n  * Light gameplay impacts\n\n### Insanity\n* Increases when Sanity drops.\n* Introduces hallucinations, screen effects and sound cues.\n\n### Tempo\n* Default maximum: **120**\n* Does **not** regenerate naturally.\n* Gained by:\n  * Dealing damage\n  * Taking damage\n* Gradually decreases when out of combat.\n* If **Iron’s Spells & Spellbooks** is installed, Tempo increases mana regeneration.\n* **Vent Ability:**\n  * Press **G** (rebindable) to perform a short-range pulse that pushes nearby enemies back.\n  * Costs **40 Tempo**.\n  * Intended as a defensive tool for escaping danger or creating space",
  "categories": [
    "adventure",
    "forge",
    "game-mechanics",
    "magic",
    "utility"
  ],
  "client_side": "required",
  "server_side": "required",
  "downloads": 830,
  "followers": 0,
  "game_versions": [
    "1.20.1"
  ],
  "date_updated": null
}