{
  "id": "jo9J4Pg4",
  "slug": "missing.jar",
  "title": "missing.jar (Discontinued)",
  "description": "Beware he lurks around the world.\n\nAlways watch your back.",
  "body": "<h1><b>I see you</b></h1>\n\nYour world is corrupted and there is someone watching you.\n\nMod is discontinued.\n\nI am working on a new horror mod.\n<br>\n[https://modrinth.com/mod/version-666](https://modrinth.com/mod/version-666)\n\n<hr>\n<h1>What mod offers and what it can do</h1>\nThere is currently 3 entities in the mod and 1 dimension to be found.\n\nMod can change the time in your world, play sounds and spawn entities but nothing bad.\n\nMod can be played both in singleplayer and multiplayer.\n<hr>\nMod is currently new and will have new stuff added as time goes on\n<hr>\nBrought to you by Cool modz.\n\nOriginal mod",
  "categories": [
    "cursed",
    "neoforge"
  ],
  "client_side": "required",
  "server_side": "required",
  "downloads": 401,
  "followers": 0,
  "game_versions": [
    "1.21.1"
  ],
  "date_updated": null
}