{
  "id": "W8YyQyz4",
  "slug": "mortui",
  "title": "Mortui",
  "description": "Become a zombie!",
  "body": "This mod requires [Cardinal Components API](https://modrinth.com/mod/cardinal-components-api) for Fabric versions and [Architectury](https://modrinth.com/mod/architectury-api) for Forge versions.\n\nIn Minecraft, villagers can become zombies when killed by other zombies. The player, on the other hand, cannot. I thought it would be a neat mechanic to implement, and so this mod was created.\n\nBecoming a zombie is simple; get killed by a zombie. The term \"zombie\" includes other zombified players, as of version 3.\n\nThis mod is *technically* not required on the client, however all rendering (such as shaders, zombie arms, et cetera) happens on the client, and won't work if the mod isn't installed on the client.\n\nAs a zombie, your hotbar is reduced to just your offhand item and your mainhand item. You are incapable of interacting with villagers and you will burn in the daylight, however monsters will not attack you. All food except for golden apples, rotten flesh, and other detrimental foods will give you the hunger status effect. You are alternatively able to gain food by attacking players or villagers. You cannot swim, though you can still bob in water.\n\nThe process of curing oneself of zombification is the same as it would be for a zombie villager; the weakness status effect and a golden apple.",
  "categories": [
    "cursed",
    "fabric",
    "forge",
    "game-mechanics",
    "mobs",
    "quilt"
  ],
  "client_side": "required",
  "server_side": "required",
  "downloads": 2434,
  "followers": 0,
  "game_versions": [
    "1.18",
    "1.18.1",
    "1.18.2",
    "1.19",
    "1.19.1",
    "1.19.2",
    "1.19.3",
    "1.19.4",
    "1.20",
    "1.20.1",
    "1.20.2",
    "1.20.3",
    "1.20.4"
  ],
  "date_updated": null
}