{
  "id": "jptzM6Xy",
  "slug": "mtr34-gilgen-door-systems-apg-hd",
  "title": "[MTR3/4] Gilgen Door Systems APG",
  "description": "Resource pack that adds Gilgen Door Systems APG to Minecraft via Minecraft Transit Railway.",
  "body": "_A resource pack for Minecraft Transit Railway._\n\n# Overview\nThis resource pack is to replace the stock APG in Minecraft Transit Railway mod with Gilgen Door Systems APG as seen on the Tuen Ma Line, made by Navi_LX9702 in 2025.\n\n# Disclaimer\n\nThis resource pack is not associated with, and is not an official product of, Gilgen Door Systems or its parent, Nabtesco.",
  "categories": [
    "512x+",
    "minecraft",
    "realistic"
  ],
  "client_side": "required",
  "server_side": "unsupported",
  "downloads": 501,
  "followers": 0,
  "game_versions": [
    "1.17.1",
    "1.18.2",
    "1.19.2",
    "1.19.4",
    "1.20.4"
  ],
  "date_updated": null
}