{
  "id": "qUbxpIPN",
  "slug": "repurposed-structures-better-dungeons-compat",
  "title": "Repurposed Structures - Better Dungeons Compat",
  "description": "Change RS Dungeons to be in Better Dungeon's style",
  "body": "Add this datapack to the game to make Repurposed Structures's dungeons be in the same style as the small dungeons from Yung's Better Dungeons mod. Note: due to some technical limitations, there many sometimes be floating blocks in the RS dungeons affected by this datapack and it may not match Better Dungeon's behavior exactly. This is to only copy Better Dungeon's Small Dungeons and not their giant ones.\n\n- Yung's Better Dungeons mod can be obtained from here: https://modrinth.com/mod/yungs-better-dungeons\n\n- Repurposed Structures mod can be obtained from here: https://modrinth.com/mod/repurposed-structures-forge\n\n\n![https://cdn.modrinth.com/data/qUbxpIPN/images/0bb85455a4768ec7758bf6c1d0e7376d86b1de7d.png](https://cdn.modrinth.com/data/qUbxpIPN/images/0bb85455a4768ec7758bf6c1d0e7376d86b1de7d.png)\n\n\n**Note:** for people using CurseForge Launcher to download datapacks, use mods like Global Data & Resourcespacks to automatically load in downloaded datapacks without needing to manually move the datapacks from the resourcepack folder to the correct folders. \nhttps://modrinth.com/mod/globalpacks",
  "categories": [
    "datapack",
    "worldgen"
  ],
  "client_side": "optional",
  "server_side": "required",
  "downloads": 2354982,
  "followers": 0,
  "game_versions": [
    "1.18.2",
    "1.19.2",
    "1.19.3",
    "1.20.1",
    "1.20.4",
    "1.21.1"
  ],
  "date_updated": null
}