{
  "id": "pspJHkH4",
  "slug": "semi-realistic-moon-vp",
  "title": "Semi-Realistic Moon (Vanilla Phases)",
  "description": "Makes Minecraft's moon look more like the real Moon, while keeping the bad astronomy.",
  "body": "Changes the Moon texture to look like a square version of the Moon in real life, while keeping a low-ish resolution to fit with vanilla.\n\nThis version matches the vanilla moon texture, but it is not physically correct. Minecraft's moon is rotatetd 90° from reality, and the phases are either reversed or go based on when it's setting.\n\nThe (better) version with the proper phases and moon rotation is [available here.](https://modrinth.com/project/semi-realistic-moon) It looks very good with shaders that have a sun/moon angle.\n\n![.gif of the phases](https://cdn.modrinth.com/data/cached_images/1cb13034fa4f9e999a20e646be8b333e7740bd6d.gif)\n\nShould be compatible with all versions going forward and back, unless Mojang messes with the folder structure.",
  "categories": [
    "32x",
    "environment",
    "minecraft",
    "realistic",
    "tweaks",
    "vanilla-like"
  ],
  "client_side": "required",
  "server_side": "unsupported",
  "downloads": 453,
  "followers": 0,
  "game_versions": [
    "1.6.4",
    "1.7.2",
    "1.7.3",
    "1.7.4",
    "1.7.5",
    "1.7.6",
    "1.7.7",
    "1.7.8",
    "1.7.9",
    "1.7.10",
    "1.8",
    "1.8.1",
    "1.8.2",
    "1.8.3",
    "1.8.4",
    "1.8.5",
    "1.8.6",
    "1.8.7",
    "1.8.8",
    "1.8.9",
    "1.9",
    "1.9.1",
    "1.9.2",
    "1.9.3",
    "1.9.4",
    "1.10",
    "1.10.1",
    "1.10.2",
    "1.11",
    "1.11.1",
    "1.11.2",
    "1.12",
    "1.12.1",
    "1.12.2",
    "1.13",
    "1.13.1",
    "1.13.2",
    "1.14",
    "1.14.1",
    "1.14.2",
    "1.14.3",
    "1.14.4",
    "1.15",
    "1.15.1",
    "1.15.2",
    "1.16",
    "1.16.1",
    "1.16.2",
    "1.16.3",
    "1.16.4",
    "1.16.5",
    "1.17",
    "1.17.1",
    "1.18",
    "1.18.1",
    "1.18.2",
    "1.19",
    "1.19.1",
    "1.19.2",
    "1.19.3",
    "1.19.4",
    "1.20",
    "1.20.1",
    "1.20.2",
    "1.20.3",
    "1.20.4",
    "1.20.5",
    "1.20.6",
    "1.21",
    "1.21.1",
    "1.21.2",
    "1.21.3",
    "1.21.4",
    "1.21.5"
  ],
  "date_updated": null
}