{
  "id": "UpYVsVtj",
  "slug": "status+",
  "title": "Status+",
  "description": "A server-side implementation of the status mod",
  "body": "A fully server-side implementation of the [status mod](https://modrinth.com/mod/status). Feature complete, including a GUI selection menu!\n\nStatus+ allows you to specify three things:\n1. Availability\n    - Open to collaboration\n    - Do not Disturb\n2. Status\n    - Are you streaming or recording?\n3. Sleep\n    - Whether you would like players to not skip the night\n\nYour current \"status\" will show up as colored icons in the tab list next to your name. To change it, simply run the `/status` command!\n\n\nCurrently there is no integration with the official mod, so you will need to remove it from your client in order to not have duplicated icons with this mod installed on the server. Proper integration is potentially planned for a future release.",
  "categories": [
    "fabric",
    "social",
    "utility"
  ],
  "client_side": "unsupported",
  "server_side": "required",
  "downloads": 395,
  "followers": 0,
  "game_versions": [
    "1.21.9",
    "1.21.10"
  ],
  "date_updated": null
}