{
  "id": "26WrP8Zx",
  "slug": "swamp-boat",
  "title": "Swamp Boat",
  "description": "Adds a swamp boat to mangrove swamps",
  "body": "**This mod adds a swamp boat to the mangrove swamps, packed with loot and villagers.**\n\n![Overview](https://cdn.modrinth.com/data/cached_images/23c1d6fbf42ea37273f5b6aa4e2853eca1da4243.jpeg)\n\n- Manned by swamp villagers, primarily fishermen.\n- Contains loot focused on fishing, scattered throughout the boat\n\n![Overview](https://cdn.modrinth.com/data/cached_images/dd86aadc77c66633b86ea193abf6b961777dfe07.jpeg)\n\n\n- The boat Spawns in mangrove swamp and warm ocean biomes.\n\n![Overview](https://cdn.modrinth.com/data/cached_images/b583d8416184199fb132dab4fd9dfc5f2e3f482c.jpeg)\n\n\nFeel free to use this mod in your modpacks",
  "categories": [
    "adventure",
    "fabric",
    "forge",
    "neoforge",
    "worldgen"
  ],
  "client_side": "required",
  "server_side": "required",
  "downloads": 9132,
  "followers": 0,
  "game_versions": [
    "1.19.2",
    "1.20.1",
    "1.21.1",
    "1.21.4",
    "1.21.8",
    "1.21.9",
    "1.21.10",
    "1.21.11"
  ],
  "date_updated": null
}