{
  "id": "Sb5ypgDP",
  "slug": "this-rocks",
  "title": "This Rocks!",
  "description": "Adds little rocks, sticks, pinecones, seashells and starfish to your world to make it feel more natural.",
  "body": "<center><p style=\"text-align: center;\">This Rocks! adds little rocks, sticks, pinecones, seashells, starfish, and geysers to your minecraft world to make it feel more natural.</p>\n<p style=\"text-align: center;\">You can break a rock to get splitters that you can craft into their respective blocks, except for the gravel rock, which drops flint.</p>\n<p style=\"text-align: center;\">The sticks drop normal minecraft sticks, the pinecones drop spruce saplings, the seashells rarely drop Nautilus Shells, and the starfish drop the starfish block for decorating.</p>\n<p style=\"text-align: center;\">The geysers get activated once you get close to them, the overworld geysers will just boost you up, but the nether geysers will burn you!</p>\n<p style=\"text-align: center;\">You can cycle through the different states of the blocks in creative mode.</p>\n<p style=\"text-align: center;\">For an even better experience, I recommend using this mod alongside <a href=\"https://www.curseforge.com/minecraft/mc-mods/wild-world\">Wild World</a>, which also adds many nice decorative worldgen features.</p>\n<p style=\"text-align: center;\"><img src=\"https://i.ibb.co/jw6nsTY/rocksbanner.png\" width=\"768\" height=\"100\" /></p>\n<p style=\"text-align: center;\">&nbsp;</p>\n<p style=\"text-align: center;\">A (Neo-)Forge port can be found here: <a href=\"https://modrinth.com/mod/this-rocks-forge\">This Rocks! (Forge)</a></p>",
  "categories": [
    "decoration",
    "fabric",
    "quilt",
    "worldgen"
  ],
  "client_side": "optional",
  "server_side": "required",
  "downloads": 1768221,
  "followers": 0,
  "game_versions": [
    "1.16.2",
    "1.16.3",
    "1.16.4",
    "1.16.5",
    "1.17-pre1",
    "1.17-pre2",
    "1.17-pre3",
    "1.17",
    "1.17.1",
    "1.18",
    "1.18.1",
    "1.18.2",
    "1.19",
    "1.19.1",
    "1.19.2",
    "1.19.4",
    "1.20",
    "1.20.1",
    "1.21",
    "1.21.1",
    "1.21.4",
    "1.21.5",
    "1.21.6",
    "1.21.7",
    "1.21.8",
    "1.21.10",
    "1.21.11"
  ],
  "date_updated": null
}