{
  "id": "S8HFDTx7",
  "slug": "uncrafting-dropper",
  "title": "Uncrafting Dropper",
  "description": "Minecraft Mod that disassembles items into their crafting components and dispenses them into the world, similar to a dispenser.",
  "body": "![Logo](https://cdn.modrinth.com/data/cached_images/fd9a80dbf24a7d5a95c34b88382038716eb848a6_0.webp)\n\n**Uncrafting Dropper:**\n\nThe Uncrafting Dropper is a utility block that allows players to reverse-craft items into their components. \nSimply place an item in the dropper, and it will attempt to break it down into its crafting ingredients.\n\nFeatures:\n\n- Reverse Crafting: Automatically disassembles items into their crafting components.\n- Damaged Item Support: Properly handles items with durability, tools , armors , weapons.\n- Redstone Integration: Can be toggled with redstone signals for automation.\n- Item Dispensing: Outputs components into the world or connected inventory.\n- Enchantments Extraction: Converts enchantments into books with a configurable drop probability.\n- Support for Custom Uncrafting Recipes\n- Tier System: Each tier upgrade improves efficiency, resource recovery and enchantment extraction.\n\n\n  <iframe width=\"560\" height=\"315\" src=\"https://www.youtube-nocookie.com/embed/3o6sJT878EA\" title=\"YouTube video player\" frameborder=\"0\" allow=\"accelerometer; autoplay; clipboard-write; encrypted-media; gyroscope; picture-in-picture; web-share\" allowfullscreen></iframe>\n  <iframe width=\"560\" height=\"315\" src=\"https://www.youtube-nocookie.com/embed/xsB4jbwSvwY\" title=\"YouTube video player\" frameborder=\"0\" allow=\"accelerometer; autoplay; clipboard-write; encrypted-media; gyroscope; picture-in-picture; web-share\" allowfullscreen></iframe>",
  "categories": [
    "forge",
    "game-mechanics",
    "management",
    "utility"
  ],
  "client_side": "required",
  "server_side": "required",
  "downloads": 774,
  "followers": 0,
  "game_versions": [
    "1.12.2"
  ],
  "date_updated": null
}